dtcc_common/__init__.py
dtcc_common/dtcc_logging.py
dtcc_common-0.7.21.dist-info/LICENSE
dtcc_common-0.7.21.dist-info/METADATA
dtcc_common-0.7.21.dist-info/WHEEL
dtcc_common-0.7.21.dist-info/top_level.txt
dtcc_common-0.7.21.dist-info/RECORD
