Metadata-Version: 2.1
Name: dtcc-common
Version: 0.7.21
Summary: DTCC Common
Author-email: Dag Wästberg <dwastberg@gmail.com>, Anders Logg <logg@chalmers.se>
Classifier: Intended Audience :: Science/Research
Classifier: Programming Language :: Python :: 3
Classifier: License :: OSI Approved :: MIT License
Requires-Python: >=3.8
License-File: LICENSE
Provides-Extra: test
Requires-Dist: pytest ; extra == 'test'
